rocrate_zenodo/__init__.py
rocrate_zenodo/authors.py
rocrate_zenodo/main.py
rocrate_zenodo/upload.py
rocrate_zenodo-0.1.1.dist-info/LICENSE
rocrate_zenodo-0.1.1.dist-info/METADATA
rocrate_zenodo-0.1.1.dist-info/WHEEL
rocrate_zenodo-0.1.1.dist-info/entry_points.txt
rocrate_zenodo-0.1.1.dist-info/RECORD
