Metadata-Version: 2.1
Name: rocrate-zenodo
Version: 0.1.1
Summary: Upload RO-Crates to Zenodo and automatically fill the Zenodo metadata
Home-page: https://www.researchobject.org/ro-crate/
License: Apache-2.0
Keywords: rocrate,RO-Crate
Author: Eli Chadwick
Author-email: eli.chadwick@manchester.ac.uk
Maintainer: Eli Chadwick
Maintainer-email: eli.chadwick@manchester.ac.uk
Requires-Python: >=3.8.1,<4.0.0
Classifier: Development Status :: 3 - Alpha
Classifier: License :: OSI Approved :: Apache Software License
Classifier: Programming Language :: Python :: 3
Classifier: Programming Language :: Python :: 3.9
Classifier: Programming Language :: Python :: 3.10
Classifier: Programming Language :: Python :: 3.11
Classifier: Programming Language :: Python :: 3.12
Classifier: Programming Language :: Python :: 3.8
Requires-Dist: rocrate (>=0.10.0,<0.11.0)
Requires-Dist: zenodo-client (>=0.3.4,<0.4.0)
Project-URL: Issues, https://github.com/ResearchObject/ro-crate-zenodo/issues
Project-URL: Repository, https://github.com/ResearchObject/ro-crate-zenodo
